Metadata-Version: 2.1
Name: p2esm
Version: 0.1.4
Summary: P2 Execution Sequence Merger
Author-email: Jean-Baptiste Delisle <jean-baptiste.delisle@unige.ch>
Project-URL: Homepage, https://gitlab.unige.ch/delisle/p2esm
Project-URL: Issues, https://gitlab.unige.ch/delisle/p2esm/-/issues
Classifier: Programming Language :: Python :: 3
Classifier: License :: OSI Approved :: GNU General Public License v3 or later (GPLv3+)
Classifier: Operating System :: OS Independent
Requires-Python: >=3.8
License-File: LICENSE
Requires-Dist: numpy
Requires-Dist: matplotlib
Requires-Dist: tk
Requires-Dist: p2api
